LICENSE.txt
pyproject.toml
setup.cfg
setup.py
./countland/__init__.py
./countland/countland.py
countland.egg-info/PKG-INFO
countland.egg-info/SOURCES.txt
countland.egg-info/dependency_links.txt
countland.egg-info/requires.txt
countland.egg-info/top_level.txt