Metadata-Version: 2.1
Name: countland
Version: 0.1.2
Summary: tools for scRNA-seq analysis
Home-page: https://github.com/shchurch/countland
Author: Samuel H. Church
Author-email: samuelhchurch@gmail.com
License: UNKNOWN
Project-URL: Bug Tracker, https://github.com/shchurch/countland/issues
Platform: UNKNOWN
Classifier: Programming Language :: Python :: 3
Classifier: License :: OSI Approved :: GNU General Public License v3 (GPLv3)
Classifier: Operating System :: OS Independent
Requires-Python: >=3.6
Provides-Extra: dev
License-File: LICENSE.txt
